revenium_middleware/__init__.py
revenium_middleware/config.py
revenium_middleware/context.py
revenium_middleware/decorators.py
revenium_middleware/metering.py
revenium_middleware-0.4.1.dist-info/licenses/LICENSE
revenium_middleware-0.4.1.dist-info/METADATA
revenium_middleware-0.4.1.dist-info/WHEEL
revenium_middleware-0.4.1.dist-info/top_level.txt
revenium_middleware-0.4.1.dist-info/RECORD
