Metadata-Version: 2.4
Name: revenium-middleware
Version: 0.4.1
Summary: A Python library that provides core functionality to send AI metering data to Revenium with decorator support.
Author-email: Revenium <support@revenium.io>
License: MIT
Project-URL: Homepage, https://github.com/revenium/revenium-middleware-core-python
Project-URL: Bug Tracker, https://github.com/revenium/revenium-middleware-core-python/issues
Project-URL: Documentation, https://github.com/revenium/revenium-middleware-core-python/blob/main/README.md
Keywords: middleware,logging,token-usage,metering,revenium
Classifier: Development Status :: 4 - Beta
Classifier: Programming Language :: Python :: 3
Classifier: Programming Language :: Python :: 3.8
Classifier: Programming Language :: Python :: 3.9
Classifier: Programming Language :: Python :: 3.10
Classifier: Programming Language :: Python :: 3.11
Classifier: Programming Language :: Python :: 3.12
Classifier: License :: OSI Approved :: MIT License
Classifier: Operating System :: OS Independent
Classifier: Intended Audience :: Developers
Classifier: Topic :: Software Development :: Libraries :: Python Modules
Requires-Python: >=3.8
License-File: LICENSE
Requires-Dist: revenium_metering>=6.8.0
Provides-Extra: openai
Requires-Dist: revenium-middleware-openai; extra == "openai"
Provides-Extra: ollama
Requires-Dist: revenium-middleware-ollama; extra == "ollama"
Provides-Extra: anthropic
Requires-Dist: revenium-middleware-anthropic; extra == "anthropic"
Provides-Extra: dev
Requires-Dist: pytest>=7.0.0; extra == "dev"
Requires-Dist: pytest-cov; extra == "dev"
Requires-Dist: flake8; extra == "dev"
Requires-Dist: black; extra == "dev"
Requires-Dist: mypy; extra == "dev"
Requires-Dist: freezegun; extra == "dev"
Dynamic: license-file
